gus/__init__.py
gus/__main__.py
gus/args.py
gus/const.py
gus/out.py
gus/urls.py
tests/__init__.py
tests/test_gus.py
gustavo-1.0.7.dist-info/LICENSE
gustavo-1.0.7.dist-info/METADATA
gustavo-1.0.7.dist-info/WHEEL
gustavo-1.0.7.dist-info/entry_points.txt
gustavo-1.0.7.dist-info/top_level.txt
gustavo-1.0.7.dist-info/RECORD
