Metadata-Version: 2.1
Name: gustavo
Version: 1.0.7
Summary: A small example package
Home-page: https://github.com/slaterslater/gustavo
Author: Anthony Slater
Author-email: slaterslater@gmail.com
License: UNKNOWN
Platform: UNKNOWN
Classifier: Programming Language :: Python :: 3
Classifier: License :: OSI Approved :: GNU General Public License v3 (GPLv3)
Classifier: Operating System :: OS Independent
Requires-Python: >=3.6
Requires-Dist: requests
Requires-Dist: progress
